setup.cfg
setup.py
ADS_BROWSER_SDK/__init__.py
ADS_BROWSER_SDK/ads.py
ADS_BROWSER_SDK/configs.py
ADS_BROWSER_SDK/errors.py
ADS_BROWSER_SDK.egg-info/PKG-INFO
ADS_BROWSER_SDK.egg-info/SOURCES.txt
ADS_BROWSER_SDK.egg-info/dependency_links.txt
ADS_BROWSER_SDK.egg-info/not-zip-safe
ADS_BROWSER_SDK.egg-info/requires.txt
ADS_BROWSER_SDK.egg-info/top_level.txt