Metadata-Version: 2.1
Name: ADS-BROWSER-SDK
Version: 0.1
Summary: Sdk for Ads-Browser
Author: arkptz1
Author-email: alisbivalka@gmail.com
